spinn/__init__.py
spinn/graphs.py
spinn/trees.py
spinn/utils.py
spinn-0.1.0.dist-info/LICENSE
spinn-0.1.0.dist-info/METADATA
spinn-0.1.0.dist-info/WHEEL
spinn-0.1.0.dist-info/top_level.txt
spinn-0.1.0.dist-info/RECORD
